scripts/__init__.py
scripts/sharding.py
torch_model_sharding-1.0.0.dist-info/METADATA
torch_model_sharding-1.0.0.dist-info/WHEEL
torch_model_sharding-1.0.0.dist-info/entry_points.txt
torch_model_sharding-1.0.0.dist-info/top_level.txt
torch_model_sharding-1.0.0.dist-info/RECORD
