Metadata-Version: 2.1
Name: torch-model-sharding
Version: 1.0.0
Summary: UNKNOWN
Home-page: UNKNOWN
Author: UNKNOWN
Author-email: UNKNOWN
License: UNKNOWN
Keywords: torch ,model,sharding
Platform: UNKNOWN
Requires-Dist: click (==8.1.6)
Requires-Dist: torch (==2.0.1)
Requires-Dist: tqdm (==4.65.0)
